wind3/__init__.py
wind3/__main__.py
wind3/exceptions.py
w3pyconnect-1.0.2.dist-info/LICENSE
w3pyconnect-1.0.2.dist-info/METADATA
w3pyconnect-1.0.2.dist-info/WHEEL
w3pyconnect-1.0.2.dist-info/top_level.txt
w3pyconnect-1.0.2.dist-info/RECORD
